allure_publisher/__init__.py
allure_publisher/__main__.py
allure_publisher/collector.py
allure_publisher/publisher.py
allure_publisher/py.typed
allure_publisher/validators.py
allure_publisher-1.1.0.dist-info/LICENSE
allure_publisher-1.1.0.dist-info/METADATA
allure_publisher-1.1.0.dist-info/WHEEL
allure_publisher-1.1.0.dist-info/top_level.txt
allure_publisher-1.1.0.dist-info/RECORD
