Metadata-Version: 2.1
Name: allure-publisher
Version: 1.1.0
Summary: Утилита для публикации результатов тестов в приемник allure-report-service
Home-page: https://github.com/Gwinkamp/allure-results-publisher
Author: Gwinkamp
License: MIT
Keywords: tools
Classifier: Topic :: Utilities
Requires-Python: >=3.10
License-File: LICENSE
Requires-Dist: typer >=0.7.0
Requires-Dist: httpx >=0.25.0
